{
	"Default": {
		"Settings": {
			"Switch":true,
			"Type": "Official",
			"Types": ["Official", "Translate"],
			"Languages": ["ZH", "EN"],
			"CacheSize": 100
		}
	},
	"Universal": {
		"Settings": {
			"Switch": true,
			"Types": ["Official", "Translate"],
			"Languages": ["ZH", "EN"]
		}
	},
	"YouTube": {
		"Settings": {
			"Switch": true,
			"Type": "Official"
		}
	},
	"Netflix": {
		"Settings": {
			"Switch": true,
			"Type": "Translate",
			"Languages": ["ZH", "EN"]
		}
	},
	"Official": {
		"Settings": {
			"CacheSize": 100,
			"Position": "Forward",
			"Offset": 0,
			"Tolerance": 1000
		}
	},
	"Translate": {
		"Settings": {
			"Type": "Google",
			"Types": ["Google", "GoogleCloud", "Azure", "DeepL"],
			"ShowOnly": false,
			"Position": "Forward",
			"CacheSize": 10,
			"Method": "Part",
			"Times": 3,
			"Interval": 100,
			"Exponential": true
		}
	},
	"External": {
		"Settings": {
			"URL": null,
			"ShowOnly": false,
			"Position": "Forward",
			"Offset": 0,
			"Tolerance": 1000
		}
	},
	"API": {
		"Settings": {
			"GoogleCloud": {
				"Mode": "Key",
				"Auth": null
			},
			"Azure": {
				"Version": "Azure",
				"Region": null,
				"Mode": "Key",
				"Auth": null
			},
			"DeepL": {
				"Version": "Free",
				"Auth": null
			}
		}
	}
}
